{
  "modelos": [
    {
      "id": 1,
      "nome": "Modelo 1",
      "colecao": "Coleção 1",
      "responsavel": "Felipe",
      "tipo": "tenis",
      "bordado": true,
      "estampado": false
    },
    {
      "id": 2,
      "nome": "Modelo 2",
      "colecao": "Coleção 2",
      "responsavel": "Thiago",
      "tipo": "tenis",
      "bordado": true,
      "estampado": false
    },
    {
      "id": 3,
      "nome": "Modelo 224",
      "responsavel": "Thiago",
      "tipo": "tenis",
      "colecao": "Coleção 2",
      "bordado": true,
      "estampa": null,
      "bordadoNao": null,
      "estampaNao": null
    },
    {
      "nome": "Modelo 23",
      "responsavel": "Thiago",
      "tipo": "tenis",
      "colecao": "Coleção 2",
      "bordado": true,
      "estampa": null,
      "id": 4
    },
    {
      "nome": "Modelo 25",
      "responsavel": "Thiago",
      "tipo": "tenis",
      "colecao": "Coleção 2",
      "bordado": true,
      "estampa": null,
      "id": 5
    },
    {
      "id": 6,
      "nome": "Modelo 27",
      "responsavel": "Thiago",
      "tipo": "bermuda",
      "colecao": "inverno",
      "bordado": false,
      "estampa": false,
      "bordadoNao": true,
      "estampaNao": true
    },
    {
      "id": 7,
      "nome": "Modelo 27",
      "responsavel": "Thiago",
      "tipo": "bermuda",
      "colecao": "Coleção 3",
      "bordado": true,
      "estampa": null,
      "bordadoNao": null,
      "estampaNao": null
    },
    {
      "id": 8,
      "nome": "sasas",
      "responsavel": "ssss",
      "tipo": "bermuda",
      "colecao": "Coleção 2",
      "bordado": null,
      "estampa": null,
      "bordadoNao": null,
      "estampaNao": null
    },
    {
      "id": 9,
      "nome": "sasa",
      "responsavel": "sasasa",
      "tipo": "bermuda",
      "colecao": "Coleção 1",
      "bordado": true,
      "estampa": true,
      "bordadoNao": null,
      "estampaNao": null
    }
  ],
  "colecoes": [
    {
      "id": 1,
      "nome": "Coleção 1",
      "estacao": "Verão",
      "responsavel": "Felipe",
      "marca": "nike",
      "anoLancamento": 2022,
      "orcamento": 20000
    },
    {
      "id": 2,
      "nome": "Coleção 2",
      "estacao": "inverno",
      "responsavel": "Thiago",
      "marca": "Adidas",
      "anoLancamento": 2022,
      "orcamento": 35000
    },
    {
      "id": 3,
      "nome": "Coleção 3",
      "estacao": "Primavera",
      "responsavel": "Pedro",
      "marca": "Renner",
      "anoLancamento": 2023,
      "orcamento": 35000
    }
  ]
}